[{"accid":1234,"accno":987654,"action_state":"INS_CONF","activation_condition":{"trailing_value":12.5,"trigger_condition":">=","trigger_value":110.0,"type":"STOP_ACTPRICE_PERC"},"modified":1700000000000,"open_volume":50,"order_id":555,"order_state":"ON_MARKET","order_type":"LIMIT","price":{"currency":"SEK","value":101.5},"price_condition":"LIMIT","reference":"my-ref","side":"BUY","tradable":{"identifier":"101","market_id":11},"traded_volume":25,"validity":{"type":"UNTIL_DATE","valid_until":1701000000000},"volume":100,"volume_condition":"NORMAL"}]
